README.md
setup.py
stockmarkettools/__init__.py
stockmarkettools/get_stock_all.py
stockmarkettools.egg-info/PKG-INFO
stockmarkettools.egg-info/SOURCES.txt
stockmarkettools.egg-info/dependency_links.txt
stockmarkettools.egg-info/requires.txt
stockmarkettools.egg-info/top_level.txt